MANIFEST.in
README.rst
setup.py
django_minimizer.egg-info/PKG-INFO
django_minimizer.egg-info/SOURCES.txt
django_minimizer.egg-info/dependency_links.txt
django_minimizer.egg-info/requires.txt
django_minimizer.egg-info/top_level.txt
djangominimizer/.DS_Store
djangominimizer/__init__.py
djangominimizer/__init__.pyc
djangominimizer/cache.py
djangominimizer/cache.pyc
djangominimizer/context_processors.py
djangominimizer/context_processors.pyc
djangominimizer/models.py
djangominimizer/models.pyc
djangominimizer/settings.py
djangominimizer/settings.pyc
djangominimizer/tests.py
djangominimizer/utils.py
djangominimizer/utils.pyc
djangominimizer/views.py
djangominimizer/management/__init__.py
djangominimizer/management/__init__.pyc
djangominimizer/management/commands/__init__.py
djangominimizer/management/commands/__init__.pyc
djangominimizer/management/commands/collectstatic.py
djangominimizer/management/commands/collectstatic.pyc
djangominimizer/migrations/0001_initial.py
djangominimizer/migrations/0001_initial.pyc
djangominimizer/migrations/0002_auto__del_field_minimizer_script_name.py
djangominimizer/migrations/0002_auto__del_field_minimizer_script_name.pyc
djangominimizer/migrations/__init__.py
djangominimizer/migrations/__init__.pyc
djangominimizer/static/.DS_Store
djangominimizer/static/minimizer/.DS_Store
djangominimizer/static/minimizer/js/coffee-script-1.1.3.min.js
djangominimizer/static/minimizer/js/jquery-1.7.min.js
djangominimizer/static/minimizer/js/less-1.1.5.min.js
djangominimizer/static/minimizer/js/modernizr-2.0.6.min.js
djangominimizer/templates/minimizer/base.html
djangominimizer/templates/minimizer/tags/scripts.html
djangominimizer/templates/minimizer/tags/styles.html
djangominimizer/templatetags/__init__.py
djangominimizer/templatetags/__init__.pyc
djangominimizer/templatetags/minimizer_tags.py
djangominimizer/templatetags/minimizer_tags.pyc
djangominimizer/tools/yuicompressor-2.4.7.jar
djangominimizer/tools/node_modules/coffee-script/.npmignore
djangominimizer/tools/node_modules/coffee-script/LICENSE
djangominimizer/tools/node_modules/coffee-script/bin/coffee
djangominimizer/tools/node_modules/coffee-script/lib/coffee-script/browser.js
