Metadata-Version: 1.0
Name: django-minimizer
Version: 0.1.4
Summary: Django application for minimizing static files and using simple html5 template
Home-page: http://django-minimizer.alageek.com
Author: Gökmen Görgen
Author-email: gokmen@alageek.com
License: GPLv3
Keywords: django application html5 yui compressor jquery modernizr
Platform: UNKNOWN
